README.rst
setup.py
torch_model_hub/activations.py
torch_model_hub/norm.py
torch_model_hub.egg-info/PKG-INFO
torch_model_hub.egg-info/SOURCES.txt
torch_model_hub.egg-info/dependency_links.txt
torch_model_hub.egg-info/not-zip-safe
torch_model_hub.egg-info/requires.txt
torch_model_hub.egg-info/top_level.txt
torch_model_hub/model/_2d_models.py
torch_model_hub/model/__init__.py
torch_model_hub/model/_attention.py
torch_model_hub/model/_text_cnn.py
torch_model_hub/model/embedding.py
torch_model_hub/model/layer.py
torch_model_hub/model/rotary_emb.py